A2-210905368-DSDL/LAB-1/Q2/q2b.v
module q2b(a,b,c,d,f);
input a,b,c,d;
output f;
assign f=(~(a&b))^c^d;
assign g=~(b|c|d);
endmodule

A2-210905368-DSDL/LAB-1/Q2/q2b_tb.v
`timescale 1ns/1ns
`include "q2b.v"

module q2b_tb();
reg a,b,c,d;
wire f,g;

q2b q2b(a,b,c,d,f);
initial
begin

$dumpfile("q2b_tb.vcd");
$dumpvars(0,q2b_tb);

a=1'b0; b=1'b0; c=1'b0; d=1'b0; #20;
a=1'b0; b=1'b0; c=1'b0; d=1'b1; #20;
a=1'b0; b=1'b0; c=1'b1; d=1'b0; #20;
a=1'b0; b=1'b0; c=1'b1; d=1'b1; #20;
a=1'b0; b=1'b1; c=1'b0; d=1'b0; #20;
a=1'b0; b=1'b1; c=1'b0; d=1'b1; #20;
a=1'b0; b=1'b1; c=1'b1; d=1'b0; #20;
a=1'b0; b=1'b1; c=1'b1; d=1'b1; #20;
a=1'b1; b=1'b0; c=1'b0; d=1'b0; #20;
a=1'b1; b=1'b0; c=1'b0; d=1'b1; #20;
a=1'b1; b=1'b0; c=1'b1; d=1'b0; #20;
a=1'b1; b=1'b0; c=1'b1; d=1'b1; #20;
a=1'b1; b=1'b1; c=1'b0; d=1'b0; #20;
a=1'b1; b=1'b1; c=1'b0; d=1'b1; #20;
a=1'b1; b=1'b1; c=1'b1; d=1'b0; #20;
a=1'b1; b=1'b1; c=1'b1; d=1'b1; #20;

$display("Test Complete");

end

endmodule

A2-210905368-DSDL/LAB-1/Q2/q2b_tb.vcd
$date
	Thu Aug 18 10:59:14 2022
$end
$version
	Icarus Verilog
$end
$timescale
	1ns
$end
$scope module q2b_tb $end
$var wire 1 ! f $end
$var reg 1 " a $end
$var reg 1 # b $end
$var reg 1 $ c $end
$var reg 1 % d $end
$scope module q2b $end
$var wire 1 " a $end
$var wire 1 # b $end
$var wire 1 $ c $end
$var wire 1 % d $end
$var wire 1 ! f $end
$var wire 1 & g $end
$upscope $end
$upscope $end
$enddefinitions $end
#0
$dumpvars
1&
0%
0$
0#
0"
1!
$end
#20
0&
0!
1%
#40
0%
1$
#60
1!
1%
#80
0%
0$
1#
#100
0!
1%
#120
0%
1$
#140
1!
1%
#160
1&
0%
0$
0#
1"
#180
0&
0!
1%
#200
0%
1$
#220
1!
1%
#240
0!
0%
0$
1#
#260
1!
1%
#280
0%
1$
#300
0!
1%
